setup.py
yas3fs/RecoverYas3fsPlugin.py
yas3fs/YAS3FSPlugin.py
yas3fs/__init__.py
yas3fs/_version.py
yas3fs/fuse.py
yas3fs.egg-info/PKG-INFO
yas3fs.egg-info/SOURCES.txt
yas3fs.egg-info/dependency_links.txt
yas3fs.egg-info/entry_points.txt
yas3fs.egg-info/requires.txt
yas3fs.egg-info/top_level.txt