Metadata-Version: 1.0
Name: yas3fs
Version: 2.3.5
Summary: YAS3FS (Yet Another S3-backed File System) is a Filesystem in Userspace (FUSE) interface to Amazon S3.
Home-page: https://github.com/danilop/yas3fs
Author: Danilo Poccia
Author-email: dpoccia@gmail.com
License: UNKNOWN
Platform: UNKNOWN
